sparkgeo_awscdk_construct_lib/__init__.py
sparkgeo_awscdk_construct_lib/py.typed
sparkgeo_awscdk_construct_lib/_jsii/__init__.py
sparkgeo_awscdk_construct_lib/_jsii/awscdk-constructs-library@0.0.13.jsii.tgz
sparkgeo_awscdk_construct_lib-0.0.13.dist-info/LICENSE
sparkgeo_awscdk_construct_lib-0.0.13.dist-info/METADATA
sparkgeo_awscdk_construct_lib-0.0.13.dist-info/WHEEL
sparkgeo_awscdk_construct_lib-0.0.13.dist-info/top_level.txt
sparkgeo_awscdk_construct_lib-0.0.13.dist-info/RECORD
